unique_orchestrator/config.py
unique_orchestrator/prompts/generic_reference_prompt.jinja2
unique_orchestrator/prompts/system_prompt.jinja2
unique_orchestrator/prompts/user_message_prompt.jinja2
unique_orchestrator/tests/test_unique_ai_get_filtered_user_metadata.py
unique_orchestrator/tests/test_unique_ai_log_tool_calls.py
unique_orchestrator/tests/test_unique_ai_reference_order.py
unique_orchestrator/tests/test_unique_ai_update_debug_info_for_tool_control.py
unique_orchestrator/unique_ai.py
unique_orchestrator/unique_ai_builder.py
unique_orchestrator-1.11.7.dist-info/LICENSE
unique_orchestrator-1.11.7.dist-info/METADATA
unique_orchestrator-1.11.7.dist-info/WHEEL
unique_orchestrator-1.11.7.dist-info/RECORD
