Metadata-Version: 2.1
Name: unique_orchestrator
Version: 1.11.7
Summary: 
License: Proprietary
Author: Andreas Hauri
Author-email: andreas.hauri@unique.ai
Requires-Python: >=3.12,<4.0
Classifier: License :: Other/Proprietary License
Classifier: Programming Language :: Python :: 3
Classifier: Programming Language :: Python :: 3.12
Requires-Dist: pydantic (>=2.8.2,<3.0.0)
Requires-Dist: pydantic-settings (>=2.10.1,<3.0.0)
Requires-Dist: python-dotenv (>=1.0.1,<2.0.0)
Requires-Dist: typing-extensions (>=4.9.0,<5.0.0)
Requires-Dist: unique-deep-research (>=3.0.17,<4.0.0)
Requires-Dist: unique-follow-up-questions (>=1.1.2,<2.0.0)
Requires-Dist: unique-internal-search (>=1.2.15,<2.0.0)
Requires-Dist: unique-sdk (>=0.10.48,<0.11.0)
Requires-Dist: unique-stock-ticker (>=1.0.2,<2.0.0)
Requires-Dist: unique-swot (>=1.0.0,<2.0.0)
Requires-Dist: unique-toolkit (>=1.42.9,<2.0.0)
Requires-Dist: unique-web-search (>=1.7.5,<2.0.0)
